<?xml version="1.0" encoding="UTF-8"?>
<node>
<version>6</version>
<dict>
  <key>expanded</key><false/>
  <key>title</key><string>Exam</string>
  <key>nodeid</key><string>864f4ca3-e331-4e6a-ae33-dcd66f608d32</string>
  <key>modified_time</key><integer>1498911613</integer>
  <key>version</key><integer>6</integer>
  <key>content_type</key><string>application/x-notebook-dir</string>
  <key>created_time</key><integer>1498911613</integer>
  <key>info_sort_dir</key><integer>1</integer>
  <key>order</key><integer>11</integer>
  <key>info_sort</key><string>order</string>
</dict>
</node>
